django_easy_error/__init__.py
django_easy_error/handlers.py
django_easy_error/utils.py
django_easy_error/templates/simple_error/default.html
django_easy_error-1.0.2.dist-info/LICENSE.txt
django_easy_error-1.0.2.dist-info/METADATA
django_easy_error-1.0.2.dist-info/WHEEL
django_easy_error-1.0.2.dist-info/top_level.txt
django_easy_error-1.0.2.dist-info/RECORD
