Metadata-Version: 2.1
Name: django-easy-error
Version: 1.0.2
Summary: Easy template integration for django error pages
Home-page: UNKNOWN
Author: Daniel Perrefort
License: GPL v3
Keywords: Django HTTP Error Pages
Platform: UNKNOWN
Classifier: Natural Language :: English
Classifier: Operating System :: OS Independent
Classifier: Programming Language :: Python
Classifier: Programming Language :: Python :: 3
Classifier: Programming Language :: Python :: 3.6
Classifier: Programming Language :: Python :: 3.7
Classifier: Programming Language :: Python :: 3.8
Classifier: Programming Language :: Python :: 3.9
Requires-Python: >=3.6
License-File: LICENSE.txt
Requires-Dist: django
